nonebot_plugin_memes_api/__init__.py
nonebot_plugin_memes_api/api/__init__.py
nonebot_plugin_memes_api/api/image_operations.py
nonebot_plugin_memes_api/api/tools.py
nonebot_plugin_memes_api/config.py
nonebot_plugin_memes_api/exception.py
nonebot_plugin_memes_api/manager.py
nonebot_plugin_memes_api/matchers/__init__.py
nonebot_plugin_memes_api/matchers/command.py
nonebot_plugin_memes_api/matchers/help.py
nonebot_plugin_memes_api/matchers/image_operations.py
nonebot_plugin_memes_api/matchers/info.py
nonebot_plugin_memes_api/matchers/manage.py
nonebot_plugin_memes_api/matchers/search.py
nonebot_plugin_memes_api/matchers/statistics.py
nonebot_plugin_memes_api/matchers/utils.py
nonebot_plugin_memes_api/migrations/1ad5a608c9e0_init_db.py
nonebot_plugin_memes_api/migrations/ba63ee20dbc1_data_migrate.py
nonebot_plugin_memes_api/recorder.py
nonebot_plugin_memes_api/utils.py
nonebot_plugin_memes_api-0.5.1.dist-info/LICENSE
nonebot_plugin_memes_api-0.5.1.dist-info/METADATA
nonebot_plugin_memes_api-0.5.1.dist-info/WHEEL
nonebot_plugin_memes_api-0.5.1.dist-info/RECORD
