Metadata-Version: 2.3
Name: nonebot_plugin_memes_api
Version: 0.5.1
Summary: Nonebot2 plugin for making memes
License: MIT
Author: meetwq
Author-email: meetwq@gmail.com
Requires-Python: >=3.9,<4.0
Classifier: License :: OSI Approved :: MIT License
Classifier: Programming Language :: Python :: 3
Classifier: Programming Language :: Python :: 3.9
Classifier: Programming Language :: Python :: 3.10
Classifier: Programming Language :: Python :: 3.11
Classifier: Programming Language :: Python :: 3.12
Classifier: Programming Language :: Python :: 3.13
Requires-Dist: filetype (>=1.2.0,<2.0.0)
Requires-Dist: httpx (>=0.20.0,<1.0.0)
Requires-Dist: nonebot-plugin-alconna (>=0.46.3,<1.0.0)
Requires-Dist: nonebot-plugin-localstore (>=0.6.0,<1.0.0)
Requires-Dist: nonebot-plugin-orm (>=0.7.0,<1.0.0)
Requires-Dist: nonebot-plugin-uninfo (>=0.6.1,<1.0.0)
Requires-Dist: nonebot2 (>=2.3.0,<3.0.0)
Requires-Dist: python-dateutil (>=2.8.2,<3.0.0)
Requires-Dist: pyyaml (>=6.0,<7.0)
Project-URL: Homepage, https://github.com/noneplugin/nonebot-plugin-memes-api
Project-URL: Repository, https://github.com/noneplugin/nonebot-plugin-memes-api
